<?xml version="1.0" ?>
<annotation>
  <folder>_annotations</folder>
  <filename>P8130278.JPG</filename>
  <path>datasets\Solenopsis_geminata\_annotations</path>
  <source>
    <database>Unknown</database>
  </source>
  <size>
    <width>3072</width>
    <height>2304</height>
    <depth>3</depth>
  </size>
  <segmented>0</segmented>
  <object>
    <name>Solenopsis_geminata</name>
    <pose>Unspecified</pose>
    <truncated>0</truncated>
    <difficult>0</difficult>
    <bndbox>
      <xmin>374</xmin>
      <ymin>1700</ymin>
      <xmax>521</xmax>
      <ymax>1898</ymax>
    </bndbox>
  </object>
</annotation>
