<?xml version="1.0" ?>
<annotation>
  <folder>Solenopsis_geminata_annotations</folder>
  <filename>20221006_090022.jpg</filename>
  <path>datasets\Solenopsis_geminata\Solenopsis_geminata_annotations</path>
  <source>
    <database>Unknown</database>
  </source>
  <size>
    <width>4032</width>
    <height>3024</height>
    <depth>3</depth>
  </size>
  <segmented>0</segmented>
  <object>
    <name>Solenopsis_geminata</name>
    <pose>Unspecified</pose>
    <truncated>0</truncated>
    <difficult>0</difficult>
    <bndbox>
      <xmin>1814</xmin>
      <ymin>0</ymin>
      <xmax>2058</xmax>
      <ymax>262</ymax>
    </bndbox>
  </object>
  <object>
    <name>Solenopsis_geminata</name>
    <pose>Unspecified</pose>
    <truncated>0</truncated>
    <difficult>0</difficult>
    <bndbox>
      <xmin>1582</xmin>
      <ymin>941</ymin>
      <xmax>1898</xmax>
      <ymax>1192</ymax>
    </bndbox>
  </object>
  <object>
    <name>Solenopsis_geminata</name>
    <pose>Unspecified</pose>
    <truncated>0</truncated>
    <difficult>0</difficult>
    <bndbox>
      <xmin>1662</xmin>
      <ymin>1213</ymin>
      <xmax>1911</xmax>
      <ymax>1437</ymax>
    </bndbox>
  </object>
</annotation>
